{
  "formatVersion": 1,
  "database": {
    "version": 11,
    "identityHash": "9808aad0b4ab4c365a1a687b742f5443",
    "entities": [
      {
        "tableName": "background",
        "createSql": "CREATE TABLE IF NOT EXISTS `${TABLE_NAME}` (`id` TEXT NOT NULL, `title` TEXT NOT NULL, `src` TEXT NOT NULL, `text_color` TEXT NOT NULL, PRIMARY KEY(`id`))",
        "fields": [
          {
            "fieldPath": "id",
            "columnName": "id",
            "affinity": "TEXT",
            "notNull": true
          },
          {
            "fieldPath": "title",
            "columnName": "title",
            "affinity": "TEXT",
            "notNull": true
          },
          {
            "fieldPath": "src",
            "columnName": "src",
            "affinity": "TEXT",
            "notNull": true
          },
          {
            "fieldPath": "text_color",
            "columnName": "text_color",
            "affinity": "TEXT",
            "notNull": true
          }
        ],
        "primaryKey": {
          "columnNames": [
            "id"
          ],
          "autoGenerate": false
        },
        "indices": [],
        "foreignKeys": []
      },
      {
        "tableName": "book",
        "createSql": "CREATE TABLE IF NOT EXISTS `${TABLE_NAME}` (`id` INTEGER NOT NULL, `title` TEXT NOT NULL, `thumbnailSrc` TEXT NOT NULL, `locallyCreated` INTEGER NOT NULL DEFAULT 0, PRIMARY KEY(`id`))",
        "fields": [
          {
            "fieldPath": "id",
            "columnName": "id",
            "affinity": "INTEGER",
            "notNull": true
          },
          {
            "fieldPath": "title",
            "columnName": "title",
            "affinity": "TEXT",
            "notNull": true
          },
          {
            "fieldPath": "thumbnailSrc",
            "columnName": "thumbnailSrc",
            "affinity": "TEXT",
            "notNull": true
          },
          {
            "fieldPath": "created",
            "columnName": "locallyCreated",
            "affinity": "INTEGER",
            "notNull": true,
            "defaultValue": "0"
          }
        ],
        "primaryKey": {
          "columnNames": [
            "id"
          ],
          "autoGenerate": false
        },
        "indices": [],
        "foreignKeys": []
      },
      {
        "tableName": "child",
        "createSql": "CREATE TABLE IF NOT EXISTS `${TABLE_NAME}` (`id` TEXT NOT NULL, `name` TEXT NOT NULL, `star` INTEGER NOT NULL, `coin` INTEGER NOT NULL, `enableReadToMe` INTEGER NOT NULL, `parentId` TEXT, `pictureId` INTEGER, PRIMARY KEY(`id`))",
        "fields": [
          {
            "fieldPath": "id",
            "columnName": "id",
            "affinity": "TEXT",
            "notNull": true
          },
          {
            "fieldPath": "name",
            "columnName": "name",
            "affinity": "TEXT",
            "notNull": true
          },
          {
            "fieldPath": "star",
            "columnName": "star",
            "affinity": "INTEGER",
            "notNull": true
          },
          {
            "fieldPath": "coin",
            "columnName": "coin",
            "affinity": "INTEGER",
            "notNull": true
          },
          {
            "fieldPath": "enableReadToMe",
            "columnName": "enableReadToMe",
            "affinity": "INTEGER",
            "notNull": true
          },
          {
            "fieldPath": "parentId",
            "columnName": "parentId",
            "affinity": "TEXT",
            "notNull": false
          },
          {
            "fieldPath": "pictureId",
            "columnName": "pictureId",
            "affinity": "INTEGER",
            "notNull": false
          }
        ],
        "primaryKey": {
          "columnNames": [
            "id"
          ],
          "autoGenerate": false
        },
        "indices": [],
        "foreignKeys": []
      },
      {
        "tableName": "book_page",
        "createSql": "CREATE TABLE IF NOT EXISTS `${TABLE_NAME}` (`id` TEXT NOT NULL, `book_id` TEXT NOT NULL, `order` INTEGER NOT NULL, `text` TEXT NOT NULL, `audio` TEXT, PRIMARY KEY(`id`), FOREIGN KEY(`book_id`) REFERENCES `book`(`id`) ON UPDATE NO ACTION ON DELETE CASCADE )",
        "fields": [
          {
            "fieldPath": "id",
            "columnName": "id",
            "affinity": "TEXT",
            "notNull": true
          },
          {
            "fieldPath": "bookId",
            "columnName": "book_id",
            "affinity": "TEXT",
            "notNull": true
          },
          {
            "fieldPath": "order",
            "columnName": "order",
            "affinity": "INTEGER",
            "notNull": true
          },
          {
            "fieldPath": "text",
            "columnName": "text",
            "affinity": "TEXT",
            "notNull": true
          },
          {
            "fieldPath": "audio",
            "columnName": "audio",
            "affinity": "TEXT",
            "notNull": false
          }
        ],
        "primaryKey": {
          "columnNames": [
            "id"
          ],
          "autoGenerate": false
        },
        "indices": [],
        "foreignKeys": [
          {
            "table": "book",
            "onDelete": "CASCADE",
            "onUpdate": "NO ACTION",
            "columns": [
              "book_id"
            ],
            "referencedColumns": [
              "id"
            ]
          }
        ]
      },
      {
        "tableName": "book_ui",
        "createSql": "CREATE TABLE IF NOT EXISTS `${TABLE_NAME}` (`bookId` INTEGER NOT NULL, `childId` INTEGER NOT NULL, `gift_opened` INTEGER NOT NULL, PRIMARY KEY(`bookId`, `childId`), FOREIGN KEY(`bookId`) REFERENCES `book`(`id`) ON UPDATE NO ACTION ON DELETE NO ACTION , FOREIGN KEY(`childId`) REFERENCES `child`(`id`) ON UPDATE NO ACTION ON DELETE NO ACTION )",
        "fields": [
          {
            "fieldPath": "bookId",
            "columnName": "bookId",
            "affinity": "INTEGER",
            "notNull": true
          },
          {
            "fieldPath": "childId",
            "columnName": "childId",
            "affinity": "INTEGER",
            "notNull": true
          },
          {
            "fieldPath": "gift_opened",
            "columnName": "gift_opened",
            "affinity": "INTEGER",
            "notNull": true
          }
        ],
        "primaryKey": {
          "columnNames": [
            "bookId",
            "childId"
          ],
          "autoGenerate": false
        },
        "indices": [
          {
            "name": "index_book_ui_bookId_childId",
            "unique": false,
            "columnNames": [
              "bookId",
              "childId"
            ],
            "orders": [],
            "createSql": "CREATE INDEX IF NOT EXISTS `index_book_ui_bookId_childId` ON `${TABLE_NAME}` (`bookId`, `childId`)"
          }
        ],
        "foreignKeys": [
          {
            "table": "book",
            "onDelete": "NO ACTION",
            "onUpdate": "NO ACTION",
            "columns": [
              "bookId"
            ],
            "referencedColumns": [
              "id"
            ]
          },
          {
            "table": "child",
            "onDelete": "NO ACTION",
            "onUpdate": "NO ACTION",
            "columns": [
              "childId"
            ],
            "referencedColumns": [
              "id"
            ]
          }
        ]
      },
      {
        "tableName": "reward_history",
        "createSql": "CREATE TABLE IF NOT EXISTS `${TABLE_NAME}` (`id` INTEGER PRIMARY KEY AUTOINCREMENT NOT NULL, `reward_type` TEXT NOT NULL, `description` TEXT NOT NULL, `count` INTEGER NOT NULL, `child_id` TEXT NOT NULL, `isComplete` INTEGER NOT NULL)",
        "fields": [
          {
            "fieldPath": "id",
            "columnName": "id",
            "affinity": "INTEGER",
            "notNull": true
          },
          {
            "fieldPath": "reward_type",
            "columnName": "reward_type",
            "affinity": "TEXT",
            "notNull": true
          },
          {
            "fieldPath": "description",
            "columnName": "description",
            "affinity": "TEXT",
            "notNull": true
          },
          {
            "fieldPath": "count",
            "columnName": "count",
            "affinity": "INTEGER",
            "notNull": true
          },
          {
            "fieldPath": "child_id",
            "columnName": "child_id",
            "affinity": "TEXT",
            "notNull": true
          },
          {
            "fieldPath": "isComplete",
            "columnName": "isComplete",
            "affinity": "INTEGER",
            "notNull": true
          }
        ],
        "primaryKey": {
          "columnNames": [
            "id"
          ],
          "autoGenerate": true
        },
        "indices": [],
        "foreignKeys": []
      },
      {
        "tableName": "book_keys",
        "createSql": "CREATE TABLE IF NOT EXISTS `${TABLE_NAME}` (`bookId` INTEGER NOT NULL, `previousKey` INTEGER, `nextKey` INTEGER, PRIMARY KEY(`bookId`))",
        "fields": [
          {
            "fieldPath": "bookId",
            "columnName": "bookId",
            "affinity": "INTEGER",
            "notNull": true
          },
          {
            "fieldPath": "previousKey",
            "columnName": "previousKey",
            "affinity": "INTEGER",
            "notNull": false
          },
          {
            "fieldPath": "nextKey",
            "columnName": "nextKey",
            "affinity": "INTEGER",
            "notNull": false
          }
        ],
        "primaryKey": {
          "columnNames": [
            "bookId"
          ],
          "autoGenerate": false
        },
        "indices": [],
        "foreignKeys": []
      },
      {
        "tableName": "selected_application",
        "createSql": "CREATE TABLE IF NOT EXISTS `${TABLE_NAME}` (`id` TEXT NOT NULL, PRIMARY KEY(`id`))",
        "fields": [
          {
            "fieldPath": "id",
            "columnName": "id",
            "affinity": "TEXT",
            "notNull": true
          }
        ],
        "primaryKey": {
          "columnNames": [
            "id"
          ],
          "autoGenerate": false
        },
        "indices": [],
        "foreignKeys": []
      },
      {
        "tableName": "profile_picture",
        "createSql": "CREATE TABLE IF NOT EXISTS `${TABLE_NAME}` (`id` INTEGER NOT NULL, `photo` TEXT NOT NULL, PRIMARY KEY(`id`))",
        "fields": [
          {
            "fieldPath": "id",
            "columnName": "id",
            "affinity": "INTEGER",
            "notNull": true
          },
          {
            "fieldPath": "photo",
            "columnName": "photo",
            "affinity": "TEXT",
            "notNull": true
          }
        ],
        "primaryKey": {
          "columnNames": [
            "id"
          ],
          "autoGenerate": false
        },
        "indices": [],
        "foreignKeys": []
      },
      {
        "tableName": "profile_picture_keys",
        "createSql": "CREATE TABLE IF NOT EXISTS `${TABLE_NAME}` (`profilePictureId` INTEGER NOT NULL, `previousKey` INTEGER, `nextKey` INTEGER, PRIMARY KEY(`profilePictureId`))",
        "fields": [
          {
            "fieldPath": "profilePictureId",
            "columnName": "profilePictureId",
            "affinity": "INTEGER",
            "notNull": true
          },
          {
            "fieldPath": "previousKey",
            "columnName": "previousKey",
            "affinity": "INTEGER",
            "notNull": false
          },
          {
            "fieldPath": "nextKey",
            "columnName": "nextKey",
            "affinity": "INTEGER",
            "notNull": false
          }
        ],
        "primaryKey": {
          "columnNames": [
            "profilePictureId"
          ],
          "autoGenerate": false
        },
        "indices": [],
        "foreignKeys": []
      }
    ],
    "views": [],
    "setupQueries": [
      "CREATE TABLE IF NOT EXISTS room_master_table (id INTEGER PRIMARY KEY,identity_hash TEXT)",
      "INSERT OR REPLACE INTO room_master_table (id,identity_hash) VALUES(42, '9808aad0b4ab4c365a1a687b742f5443')"
    ]
  }
}